claudia/README.md
claudia/__init__.py
claudia/claudia.py
claudia/requirements.txt
claudia/versions.py
claudia/network_setup/Dockerfile.rippled_build
claudia/network_setup/Dockerfile.rippled_install
claudia/network_setup/setup.sh
claudia/network_setup/configs/rippled/rippled_1/rippled.cfg
claudia/network_setup/configs/rippled/rippled_1/validators.txt
claudia/network_setup/configs/rippled/rippled_2/rippled.cfg
claudia/network_setup/configs/rippled/rippled_2/validators.txt
claudia/network_setup/configs/rippled/rippled_3/rippled.cfg
claudia/network_setup/configs/rippled/rippled_3/validators.txt
claudia/network_setup/configs/rippled/rippled_4/rippled.cfg
claudia/network_setup/configs/rippled/rippled_4/validators.txt
claudia/network_setup/configs/sidechain/witness/template/witness.template
claudia/network_setup/lib/build.sh
claudia/network_setup/lib/rippled_network.yml
claudia/network_setup/lib/setup_helper.sh
claudia/network_setup/lib/sidechain_network.yml
claudia/network_setup/lib/validate_network.py
claudia/network_setup/lib/witness_action.sh
claudia/network_setup/lib/xchain_bridge_create.py
claudia-0.2.dist-info/LICENSE
claudia-0.2.dist-info/METADATA
claudia-0.2.dist-info/WHEEL
claudia-0.2.dist-info/entry_points.txt
claudia-0.2.dist-info/top_level.txt
claudia-0.2.dist-info/RECORD
