Metadata-Version: 2.1
Name: claudia
Version: 0.2
Summary: Helper utility to manage local rippled mainnet and sidechain networks
Home-page: https://xrpl.org/
Download-URL: https://github.com/ripple/claudia
Author: Kausty Saxena
Author-email: ksaxena@ripple.com
Keywords: ripple xrpl python local mainnet sidechain
License-File: LICENSE
Requires-Dist: click
Requires-Dist: PyHamcrest
Requires-Dist: setuptools
Requires-Dist: requests
Requires-Dist: inquirer
Requires-Dist: watchdog
